mp42frame.py
mp42frame-0.0.12.dist-info/METADATA
mp42frame-0.0.12.dist-info/WHEEL
mp42frame-0.0.12.dist-info/entry_points.txt
mp42frame-0.0.12.dist-info/top_level.txt
mp42frame-0.0.12.dist-info/RECORD
