Metadata-Version: 2.1
Name: mp42frame
Version: 0.0.12
Summary: convert a video file or multiple video files in a directory into a series of image frames
Home-page: https://github.com/zhdpy/mp42frame/
Author: Z.H.Ding
Author-email: zh.py.2023@gmail.com
License: UNKNOWN
Project-URL: Bug Tracker, https://github.com/zhdpy/mp42frame/
Platform: UNKNOWN
Classifier: Programming Language :: Python :: 3
Classifier: License :: OSI Approved :: MIT License
Classifier: Operating System :: OS Independent
Requires-Python: >=3.7
